{
    "version": 8,
    "configurePresets": [
        {
            "name": "windows",
            "displayName": "Windows - Visual Studio 2022",
            "description": "Visual Studio generator for Windows",
            "generator": "Visual Studio 17 2022",
            "binaryDir": "${sourceDir}/build/${presetName}",
            "architecture": {
                "value": "x64",
                "strategy": "set"
            },
            "cacheVariables": {
                "CMAKE_TOOLCHAIN_FILE": "$env{VCPKG_ROOT}/scripts/buildsystems/vcpkg.cmake"
            }
        },
        {
            "name": "mac",
            "displayName": "Mac - Ninja",
            "description": "Mac generator for macOS/Linux",
            "generator": "Ninja",
            "binaryDir": "${sourceDir}/build/${presetName}",
            "cacheVariables": {
                "CMAKE_BUILD_TYPE": "Release",
                "CMAKE_TOOLCHAIN_FILE": "$env{VCPKG_ROOT}/scripts/buildsystems/vcpkg.cmake"
            }
        }
    ],
    "buildPresets": [
        {
            "name": "windows-release",
            "configurePreset": "windows",
            "configuration": "Release"
        },
        {
            "name": "windows-debug",
            "configurePreset": "windows",
            "configuration": "Debug"
        },
        {
            "name": "mac-release",
            "configurePreset": "mac",
            "configuration": "Release"
        }
    ]
}
